[
    {
        "%vlocity_namespace%__DomainObjectAPIName__c": "Case",
        "%vlocity_namespace%__DomainObjectCreationOrder__c": 1,
        "%vlocity_namespace%__DomainObjectFieldAPIName__c": "Id",
        "%vlocity_namespace%__FormulaOrder__c": 0,
        "%vlocity_namespace%__InterfaceFieldAPIName__c": "ContextId",
        "%vlocity_namespace%__InterfaceObjectName__c": "json",
        "%vlocity_namespace%__IsDisabled__c": false,
        "%vlocity_namespace%__IsRequiredForUpsert__c": false,
        "%vlocity_namespace%__LinkCreatedIndex__c": 0,
        "%vlocity_namespace%__MapId__c": "DRCaseOwnerUpdateCustom1671",
        "%vlocity_namespace%__UpsertKey__c": false,
        "Name": "DRCaseOwnerUpdate",
        "VlocityDataPackType": "SObject",
        "VlocityRecordSObjectType": "%vlocity_namespace%__DRMapItem__c"
    },
    {
        "%vlocity_namespace%__DomainObjectAPIName__c": "Case",
        "%vlocity_namespace%__DomainObjectCreationOrder__c": 1,
        "%vlocity_namespace%__DomainObjectFieldAPIName__c": "IsEscalated",
        "%vlocity_namespace%__FormulaOrder__c": 0,
        "%vlocity_namespace%__InterfaceFieldAPIName__c": "Escalated",
        "%vlocity_namespace%__InterfaceObjectName__c": "json",
        "%vlocity_namespace%__IsDisabled__c": false,
        "%vlocity_namespace%__IsRequiredForUpsert__c": false,
        "%vlocity_namespace%__LinkCreatedIndex__c": 0,
        "%vlocity_namespace%__MapId__c": "DRCaseOwnerUpdateCustom3522",
        "%vlocity_namespace%__UpsertKey__c": false,
        "Name": "DRCaseOwnerUpdate",
        "VlocityDataPackType": "SObject",
        "VlocityRecordSObjectType": "%vlocity_namespace%__DRMapItem__c"
    },
    {
        "%vlocity_namespace%__DomainObjectAPIName__c": "Case",
        "%vlocity_namespace%__DomainObjectCreationOrder__c": 1,
        "%vlocity_namespace%__DomainObjectFieldAPIName__c": "OwnerId",
        "%vlocity_namespace%__FormulaOrder__c": 0,
        "%vlocity_namespace%__InterfaceFieldAPIName__c": "SelectNewOwner:OwnerId",
        "%vlocity_namespace%__InterfaceObjectName__c": "json",
        "%vlocity_namespace%__IsDisabled__c": false,
        "%vlocity_namespace%__IsRequiredForUpsert__c": false,
        "%vlocity_namespace%__LinkCreatedIndex__c": 0,
        "%vlocity_namespace%__MapId__c": "DRCaseOwnerUpdateCustom2881",
        "%vlocity_namespace%__UpsertKey__c": false,
        "Name": "DRCaseOwnerUpdate",
        "VlocityDataPackType": "SObject",
        "VlocityRecordSObjectType": "%vlocity_namespace%__DRMapItem__c"
    }
]